{
  "_savedAt": "2026-03-27T07:45:59.887Z",
  "type": "InvestmentAdvice",
  "userPrompt": "今天是 2026-03-27，請根據以下最新戰報資料與今日市場重點新聞，產出教練洞察：\n\n<JSON>\n【量化系統判定狀態】\n系統狀態：🌡️【偏熱/觀察】\n行動建議：👀 觀察等待 (市場偏熱，避免追高)\n\n【帳戶風控狀態】\n實際槓桿：1 倍 (目標 1.8 倍) ➔ 狀態：🛡️ 防禦狀態 (具備加碼空間)\n大盤維持率：999%\n00675L佔比：11.46% (目標上限 40%)\n現金儲備：$260,000\n持股分佈：0050 (5,863 股) / 00675L (500 股)\n\n【買進條件判定】\n總評分：0 分 (門檻 4 分) ➔ 🔴未達標\n觸發因子：跌幅 2.00%、RSI 未反轉、MACD 無交叉、KD 無交叉\n\n【風險與賣出監控】\n大盤位階：🔥【極高位階/過熱】\nVIX指數：36.22 ➔ 🔥 落入高波動區 (偏恐慌)\n過熱指標：觸發 1 個 (門檻 2)\n轉弱指標：觸發 1 個 (門檻 3)\n賣出訊號：觸發 0 次 (門檻 2)\n\n【底層策略參數配置 (供教練決策參考)】\n- 目標槓桿倍數：1.8\n- 買入分數門檻：4 分\n- 賣出觸發門檻：累積 2 個賣出訊號\n- 乖離過熱門檻：累積 2 個過熱因子\n- 轉弱確認門檻：累積 3 個轉弱因子\n- VIX 恐慌/安逸線：> 20 / < 12\n- 融資斷頭警戒線：低於 140%\n- 00675L 佔比上限：40% (硬限制 4500%)\n</JSON>\n\n<Macro_And_Chip_Status>\n【總體經濟與籌碼狀態】\n1. 美股情緒 (CNN恐懼貪婪)：21.03分 (極度恐慌)\n   趨勢：持平 / 盤整\n   解讀：進入極度恐慌，留意美股左側超跌買點\n\n2. 散戶籌碼 (大盤維持率)：176.7% (極度安全)\n   動態：融資餘額 3911.37 億 (恐慌性殺出 (-43.62億))\n   解讀：籌碼安定，無系統性斷頭風險\n\n3. 外資動向 (USD/TWD)：31.966\n   動態：急貶 (+2.3%) / 中期貶值趨勢 (+0.7192)\n   解讀：匯率波動在正常範圍內，外資無極端進出跡象，回歸基本面與個股表現。\n\n4. 長線景氣 (國發會燈號)：39分 (紅燈 (過熱))\n   位階：景氣過熱 (長線高檔區)\n   解讀：大盤處於相對高風險區，強烈建議逐步獲利了結、降低持股水位並提高現金比重，切勿重壓或過度擴張信用。\n</Macro_And_Chip_Status>\n\n<MacroAnalysis>\n【總經多空對決報告】\n最終判定方向：BEAR\n市場主軸：滯脹威脅與流動性緊縮雙重夾擊，外資加速撤離，市場進入系統性去槓桿階段。\n\n[積分對決]\n🟢 總利多分數：2\n🔴 總利空分數：20\n\n[核心驅動邏輯]\n- 避險資產黃金下跌暗示市場流動性極度枯竭。\n- 中東衝突與關稅預期構建長期通膨壓力。\n- 外資對 AI 估值轉向謹慎，台韓股市首當其衝。\n- 台股籌碼面崩壞，外資單日賣超創近期新高。\n- 經濟衰退風險上升，市場由成長轉向防禦。\n\n[當下重大驅動事件]\n利多推力：\n  [+2分] 南亞科引進四大戰略股東入股\n利空拉力：\n  [-4分] 中東衝突升級與油價測試通膨目標\n  [-4分] 三大法人單日賣超 401 億元，外資連續撤離\n  [-4分] Fed 擔憂關稅政策引發結構性通膨\n  [-3分] AI 泡沫疑慮與台積電重挫跌破關鍵位\n  [-5分] 黃金避險失效與衰退風險上升\n不確定性/未爆彈：\n  無顯著觀望事件\n</MacroAnalysis>\n\n<News_Context>\n1. [US] European shares snap win streak as Middle East conflict fans inflation worries\n   ↳ 摘要：中東衝突升級引發全球市場對能源價格與通膨的劇烈擔憂，歐洲股市結束連漲紀錄。此事件不僅推升原油成本，更可能迫使各國央行延後降息時程。對於台股大盤而言，地緣政治風險將導致避險情緒升溫，短期內資金恐持續由科技權值股流向能源或防禦型資產，壓抑 0050 等權值型 ETF 表現。\n\n2. [TW] 三大法人賣超台股401.86億元\n   ↳ 摘要：台股三大法人單日賣超達 401.86 億元，其中外資連續兩日大舉提款，今日賣超金額高達 384 億元。這顯示國際資金在面對美伊衝突與通膨不確定性時，正加速撤出新興市場。外資的大規模流出對台積電等權值股造成沉重賣壓，短期內台股籌碼面極度偏空，投資人需警惕大盤回測支撐的風險。\n\n3. [US] The Fed Is Worried About Trump-Fueled Inflation. Are Your Stocks Safe?\n   ↳ 摘要：聯準會對未來通膨路徑表示擔憂，特別是潛在的政策變動（如關稅）可能再次推升物價。市場正重新評估 Fed 的降息路徑，若通膨數據無法有效受控，高利率環境維持更久（Higher for longer）將成為常態。這將直接衝擊高槓桿投資策略的成本，並對科技股估值產生修正壓力。\n\n4. [TW] 台股跌225點力守33000點 台積電跌20元收1820元\n   ↳ 摘要：台股今日下跌 225 點，勉強守住 33,000 點大關，權王台積電重挫 20 元收在 1,820 元。台積電作為大盤風向球，其股價走弱反映了市場對半導體需求增速放緩及地緣政治干擾的恐懼。若台積電無法止跌，大盤恐將跌破關鍵心理支撐，引發進一步的技術性賣壓與融資斷頭潮。\n\n5. [US] How Are Tariffs Affecting Inflation and Stock Markets in 2026?\n   ↳ 摘要：關於 2026 年關稅政策對通膨與股市影響的討論升溫，顯示市場已開始定價長期的貿易保護主義風險。關稅增加將直接導致進口成本上升，進而轉嫁至消費者，形成結構性通膨。對於高度依賴出口的台灣半導體產業而言，這意味著未來營運成本與供應鏈複雜度將大幅增加，長期獲利能力面臨挑戰。\n\n6. [TW] AI泡沫疑慮壓頂2月外資賣超韓股金額創新高- 新聞\n   ↳ 摘要：外資 2 月份大舉賣超韓股，反映出市場對 AI 產業是否過熱及泡沫化的疑慮。由於台韓股市產業結構相似，皆以半導體與 AI 供應鏈為核心，此資金流向具有高度警示意義。若 AI 變現能力未達預期，外資可能對台股進行類似的減碼行動，投資人應密切觀察 AI 伺服器相關族群的營收實質貢獻。\n\n7. [TW] 《半導體》南亞科找來四大咖入股外資喊：記憶體玩法變了- 上市櫃\n   ↳ 摘要：南亞科引進四大戰略股東，顯示記憶體產業正經歷結構性轉型，從單純的價格競爭轉向生態系合作。雖然短期內記憶體族群股價仍受大盤拖累，但產業底部的確立與大廠入股有助於長期評價修復。這對於半導體產業鏈的完整性有正面幫助，但在總經環境惡化下，短期仍難脫離震盪格局。\n\n8. [US] Why is ‘safe haven’ gold crashing amid a war?\n   ↳ 摘要：在戰爭背景下，傳統避險資產黃金竟出現劇烈波動甚至下挫，反映出市場流動性緊縮或投資人被迫拋售資產以支應其他虧損。這種「避險失效」的現象通常出現在市場極度恐慌或資金鏈緊張時期。對於槓桿投資者而言，這是一個危險信號，暗示市場流動性可能正在枯竭，需嚴格控管倉位風險。\n\n9. [US] Crude prices test GDP, inflation goals\n   ↳ 摘要：原油價格測試各國 GDP 與通膨目標，油價若長期維持高位，將直接侵蝕企業獲利並抑制民間消費。對於能源進口依賴度高的台灣而言，油價上漲將推升輸入型通膨，迫使央行維持偏緊的貨幣政策。這對台股大盤的本益比擴張形成實質阻礙，特別是對於非電金族群的傳統產業衝擊更鉅。\n\n10. [US] Recession Risks Are Rising According To Wall Street. Here's What It Means for Investors.\n   ↳ 摘要：華爾街警告經濟衰退風險正在上升，這與通膨復燃的擔憂形成「滯脹」威脅。在衰退預期下，市場對企業盈餘增長的容忍度將降低。若後續經濟數據證實增長放緩，台股即便有 AI 題材支撐，也難以獨善其身。投資者應開始增加防禦性配置，並減少對高 beta 係數股票的過度曝險。\n</News_Context>",
  "schema": {
    "type": "OBJECT",
    "properties": {
      "coach_internal_thinking": {
        "type": "STRING",
        "description": "【隱藏思考區】教練的內部推演過程。請在此交叉分析槓桿、總經、籌碼面(維持率/融資/外資匯率)、VIX 與新聞，並思考應對策略。（此欄位不限字數，請完整推演）"
      },
      "risk_warnings": {
        "type": "ARRAY",
        "description": "⚠️ 結合當下數據 (如VIX/維持率/匯率)，用教練口吻指出具體風險。每點約 30-50 字，明確指出『因為什麼數據，所以哪裡有危險』。",
        "items": {
          "type": "STRING"
        },
        "minItems": 1,
        "maxItems": 3
      },
      "action_items": {
        "type": "ARRAY",
        "description": "✅ 下一步應對行動。必須包含具體條件與動作 (If-Then)。每點約 30-50 字。例如：『若匯率未能在 32.5 止穩，就繼續保持防禦狀態，只扣 0050。』",
        "items": {
          "type": "STRING"
        },
        "minItems": 1,
        "maxItems": 4
      },
      "mindset_advice": {
        "type": "ARRAY",
        "description": "🧭 針對客戶當前帳戶槓桿狀態，給予一句溫暖但嚴格的紀律提醒。每點約 30-50 字，幫助客戶克服恐慌或貪婪。",
        "items": {
          "type": "STRING"
        },
        "minItems": 1,
        "maxItems": 4
      }
    },
    "required": [
      "coach_internal_thinking",
      "risk_warnings",
      "action_items",
      "mindset_advice"
    ]
  },
  "rawResult": {
    "coach_internal_thinking": "目前市場正處於極度矛盾的十字路口。從量化數據看，客戶實際槓桿僅 1 倍，遠低於 1.8 倍目標，且現金儲備充足，帳戶維持率極高，處於絕對防禦狀態。然而，外部環境極其惡劣：<MacroAnalysis> 給出 -20 分的極端利空評分，VIX 飆升至 36.22 進入高波動區，CNN 恐懼貪婪指數僅 21.03 分，顯示全球資金正處於集體恐慌。新聞面證實了『滯脹』威脅（油價漲、通膨憂慮、衰退風險）與外資大舉撤離台股（單日賣超 401 億）。雖然大盤維持率 176.7% 顯示散戶尚未集體斷頭，但景氣燈號紅燈與高位階暗示長期下行風險。教練策略：雖然槓桿有空間，但『買進評分 0 分』且『外資急撤』，此時絕不應盲目加碼。應利用 1 倍槓桿的優勢，靜待 VIX 降溫與匯率止穩。這是一場耐力賽，目前的下跌是為了清洗浮額，我們手握現金，擁有隨時進場收割超跌資產的主動權，但現在還不是時候。",
    "risk_warnings": [
      "VIX 指數飆升至 36.22 且美股極度恐慌，顯示市場進入無差別拋售階段，短期內波動將劇烈放大。",
      "外資單日大賣 401 億且台幣急貶，資金正撤離權值股，台積電若失守關鍵位將引發連鎖技術性賣壓。",
      "景氣燈號紅燈與滯脹威脅並存，代表大盤處於長線高位階，任何反彈都可能面臨沈重的解套壓力。"
    ],
    "action_items": [
      "目前買進評分為 0，請嚴格執行『不加碼』指令，將 26 萬現金鎖死在帳戶，不要試圖接刀。",
      "若台幣匯率持續貶值破 32.2 元，應進一步縮減 00675L 的曝險預期，優先保護 0050 核心部位。",
      "設定台積電 1,800 元為心理防線，若跌破且放量，請保持觀望，等待 VIX 回落至 25 以下再評估。",
      "維持現有 1 倍槓桿不動，利用高維持率優勢抗震，目標是活過這波去槓桿潮，而非在低點耗盡子彈。"
    ],
    "mindset_advice": [
      "你現在 1 倍的槓桿就是最強的防彈衣。看著別人恐慌斷頭時，你要慶幸自己手握現金且沒有過度擴張。",
      "市場極度恐慌時，最不該做的就是『隨機應變』。紀律是你的唯一指南，沒到 4 分，一塊錢都不要投。",
      "記住，長期贏家不是買在最高點的人，而是當崩盤發生時，還有能力留在場內並有餘力買進的人。",
      "現在的下跌是為了修正過熱的評價，這對我們 1.8 倍槓桿的長期計畫來說，是降低成本的必經之路。"
    ]
  }
}